cache_function/__init__.py
cache_function/cache_function.py
cache_function/test_cache_function.py
cache_function_deepakmishra-0.0.3.dist-info/LICENSE
cache_function_deepakmishra-0.0.3.dist-info/METADATA
cache_function_deepakmishra-0.0.3.dist-info/WHEEL
cache_function_deepakmishra-0.0.3.dist-info/top_level.txt
cache_function_deepakmishra-0.0.3.dist-info/RECORD
