Metadata-Version: 2.1
Name: cache-function-deepakmishra
Version: 0.0.3
Summary: A small decorator which helps cache a result of a function
Home-page: https://github.com/deepakmishra/cache_function
Author: Deepak Mishra
Author-email: deepakmishra117@gmail.com
License: UNKNOWN
Platform: UNKNOWN
Classifier: Programming Language :: Python :: 2.7
Classifier: License :: Freeware
Classifier: Operating System :: OS Independent
